{"nodes": [{"id": "volumes_hdx_dev_ganesha_frontend_blazor_src_ganesha_designlab_shared_utilities_formathelper_cs", "label": "FormatHelper.cs", "file_type": "code", "source_file": "src/Ganesha.DesignLab.Shared/Utilities/FormatHelper.cs", "source_location": "L1"}, {"id": "utilities_formathelper_formathelper", "label": "FormatHelper", "file_type": "code", "source_file": "src/Ganesha.DesignLab.Shared/Utilities/FormatHelper.cs", "source_location": "L5"}, {"id": "utilities_formathelper_formathelper_formatnumber", "label": ".FormatNumber()", "file_type": "code", "source_file": "src/Ganesha.DesignLab.Shared/Utilities/FormatHelper.cs", "source_location": "L7"}, {"id": "utilities_formathelper_formathelper_formatpercentage", "label": ".FormatPercentage()", "file_type": "code", "source_file": "src/Ganesha.DesignLab.Shared/Utilities/FormatHelper.cs", "source_location": "L10"}, {"id": "utilities_formathelper_formathelper_formatcurrency", "label": ".FormatCurrency()", "file_type": "code", "source_file": "src/Ganesha.DesignLab.Shared/Utilities/FormatHelper.cs", "source_location": "L13"}, {"id": "utilities_formathelper_formathelper_formatdate", "label": ".FormatDate()", "file_type": "code", "source_file": "src/Ganesha.DesignLab.Shared/Utilities/FormatHelper.cs", "source_location": "L23"}, {"id": "datetime", "label": "DateTime", "file_type": "code", "source_file": "", "source_location": ""}, {"id": "datetimeoffset", "label": "DateTimeOffset", "file_type": "code", "source_file": "", "source_location": ""}, {"id": "utilities_formathelper_formathelper_truncatetext", "label": ".TruncateText()", "file_type": "code", "source_file": "src/Ganesha.DesignLab.Shared/Utilities/FormatHelper.cs", "source_location": "L29"}], "edges": [{"source": "volumes_hdx_dev_ganesha_frontend_blazor_src_ganesha_designlab_shared_utilities_formathelper_cs", "target": "globalization", "relation": "imports", "context": "import", "confidence": "EXTRACTED", "source_file": "src/Ganesha.DesignLab.Shared/Utilities/FormatHelper.cs", "source_location": "L1", "weight": 1.0}, {"source": "volumes_hdx_dev_ganesha_frontend_blazor_src_ganesha_designlab_shared_utilities_formathelper_cs", "target": "utilities_formathelper_formathelper", "relation": "contains", "confidence": "EXTRACTED", "source_file": "src/Ganesha.DesignLab.Shared/Utilities/FormatHelper.cs", "source_location": "L5", "weight": 1.0}, {"source": "utilities_formathelper_formathelper", "target": "utilities_formathelper_formathelper_formatnumber", "relation": "method", "confidence": "EXTRACTED", "source_file": "src/Ganesha.DesignLab.Shared/Utilities/FormatHelper.cs", "source_location": "L7", "weight": 1.0}, {"source": "utilities_formathelper_formathelper", "target": "utilities_formathelper_formathelper_formatpercentage", "relation": "method", "confidence": "EXTRACTED", "source_file": "src/Ganesha.DesignLab.Shared/Utilities/FormatHelper.cs", "source_location": "L10", "weight": 1.0}, {"source": "utilities_formathelper_formathelper", "target": "utilities_formathelper_formathelper_formatcurrency", "relation": "method", "confidence": "EXTRACTED", "source_file": "src/Ganesha.DesignLab.Shared/Utilities/FormatHelper.cs", "source_location": "L13", "weight": 1.0}, {"source": "utilities_formathelper_formathelper", "target": "utilities_formathelper_formathelper_formatdate", "relation": "method", "confidence": "EXTRACTED", "source_file": "src/Ganesha.DesignLab.Shared/Utilities/FormatHelper.cs", "source_location": "L23", "weight": 1.0}, {"source": "utilities_formathelper_formathelper_formatdate", "target": "datetime", "relation": "references", "confidence": "EXTRACTED", "source_file": "src/Ganesha.DesignLab.Shared/Utilities/FormatHelper.cs", "source_location": "L23", "weight": 1.0, "context": "parameter_type"}, {"source": "utilities_formathelper_formathelper", "target": "utilities_formathelper_formathelper_formatdate", "relation": "method", "confidence": "EXTRACTED", "source_file": "src/Ganesha.DesignLab.Shared/Utilities/FormatHelper.cs", "source_location": "L26", "weight": 1.0}, {"source": "utilities_formathelper_formathelper_formatdate", "target": "datetimeoffset", "relation": "references", "confidence": "EXTRACTED", "source_file": "src/Ganesha.DesignLab.Shared/Utilities/FormatHelper.cs", "source_location": "L26", "weight": 1.0, "context": "parameter_type"}, {"source": "utilities_formathelper_formathelper", "target": "utilities_formathelper_formathelper_truncatetext", "relation": "method", "confidence": "EXTRACTED", "source_file": "src/Ganesha.DesignLab.Shared/Utilities/FormatHelper.cs", "source_location": "L29", "weight": 1.0}], "raw_calls": [{"caller_nid": "utilities_formathelper_formathelper_formatnumber", "callee": "ToString", "is_member_call": true, "source_file": "/Volumes/HDX/Dev/ganesha-frontend-blazor/src/Ganesha.DesignLab.Shared/Utilities/FormatHelper.cs", "source_location": "L8", "receiver": null}, {"caller_nid": "utilities_formathelper_formathelper_formatpercentage", "callee": "ToString", "is_member_call": true, "source_file": "/Volumes/HDX/Dev/ganesha-frontend-blazor/src/Ganesha.DesignLab.Shared/Utilities/FormatHelper.cs", "source_location": "L11", "receiver": null}, {"caller_nid": "utilities_formathelper_formathelper_formatcurrency", "callee": "GetCultureInfoByIetfLanguageTag", "is_member_call": true, "source_file": "/Volumes/HDX/Dev/ganesha-frontend-blazor/src/Ganesha.DesignLab.Shared/Utilities/FormatHelper.cs", "source_location": "L15", "receiver": null}, {"caller_nid": "utilities_formathelper_formathelper_formatcurrency", "callee": "Equals", "is_member_call": true, "source_file": "/Volumes/HDX/Dev/ganesha-frontend-blazor/src/Ganesha.DesignLab.Shared/Utilities/FormatHelper.cs", "source_location": "L16", "receiver": null}, {"caller_nid": "utilities_formathelper_formathelper_formatcurrency", "callee": "Equals", "is_member_call": true, "source_file": "/Volumes/HDX/Dev/ganesha-frontend-blazor/src/Ganesha.DesignLab.Shared/Utilities/FormatHelper.cs", "source_location": "L17", "receiver": null}, {"caller_nid": "utilities_formathelper_formathelper_formatcurrency", "callee": "ToString", "is_member_call": true, "source_file": "/Volumes/HDX/Dev/ganesha-frontend-blazor/src/Ganesha.DesignLab.Shared/Utilities/FormatHelper.cs", "source_location": "L20", "receiver": null}, {"caller_nid": "utilities_formathelper_formathelper_formatdate", "callee": "ToString", "is_member_call": true, "source_file": "/Volumes/HDX/Dev/ganesha-frontend-blazor/src/Ganesha.DesignLab.Shared/Utilities/FormatHelper.cs", "source_location": "L24", "receiver": null}, {"caller_nid": "utilities_formathelper_formathelper_formatdate", "callee": "ToString", "is_member_call": true, "source_file": "/Volumes/HDX/Dev/ganesha-frontend-blazor/src/Ganesha.DesignLab.Shared/Utilities/FormatHelper.cs", "source_location": "L27", "receiver": null}, {"caller_nid": "utilities_formathelper_formathelper_truncatetext", "callee": "IsNullOrEmpty", "is_member_call": true, "source_file": "/Volumes/HDX/Dev/ganesha-frontend-blazor/src/Ganesha.DesignLab.Shared/Utilities/FormatHelper.cs", "source_location": "L31", "receiver": null}, {"caller_nid": "utilities_formathelper_formathelper_truncatetext", "callee": "Min", "is_member_call": true, "source_file": "/Volumes/HDX/Dev/ganesha-frontend-blazor/src/Ganesha.DesignLab.Shared/Utilities/FormatHelper.cs", "source_location": "L36", "receiver": null}, {"caller_nid": "utilities_formathelper_formathelper_truncatetext", "callee": "Concat", "is_member_call": true, "source_file": "/Volumes/HDX/Dev/ganesha-frontend-blazor/src/Ganesha.DesignLab.Shared/Utilities/FormatHelper.cs", "source_location": "L37", "receiver": null}, {"caller_nid": "utilities_formathelper_formathelper_truncatetext", "callee": "AsSpan", "is_member_call": true, "source_file": "/Volumes/HDX/Dev/ganesha-frontend-blazor/src/Ganesha.DesignLab.Shared/Utilities/FormatHelper.cs", "source_location": "L37", "receiver": null}]}